setup.py
gh_webhook/__init__.py
gh_webhook/__main__.py
gh_webhook.egg-info/PKG-INFO
gh_webhook.egg-info/SOURCES.txt
gh_webhook.egg-info/dependency_links.txt
gh_webhook.egg-info/not-zip-safe
gh_webhook.egg-info/requires.txt
gh_webhook.egg-info/top_level.txt