Metadata-Version: 1.0
Name: gh-webhook
Version: 0.1
Summary: Webhook for github
Home-page: https://github.com/GerbenAaltink/py-gdw
Author: Gerben Aaltink
Author-email: gerbenaaltink@gmail.com
License: MIT
Platform: UNKNOWN
